kcalign/__init__.py
kcalign/cli.py
kcalign-1.0.2.dist-info/LICENSE
kcalign-1.0.2.dist-info/METADATA
kcalign-1.0.2.dist-info/WHEEL
kcalign-1.0.2.dist-info/entry_points.txt
kcalign-1.0.2.dist-info/top_level.txt
kcalign-1.0.2.dist-info/RECORD
