Metadata-Version: 2.1
Name: kcalign
Version: 1.0.2
Summary: Kalgin-based codon-aware aligner for multiple sequences
Home-page: https://github.com/galaxyproject/kc-align
Author: Nick Keener
Author-email: nickeener@gmail.com
License: UNKNOWN
Platform: UNKNOWN
Classifier: Programming Language :: Python :: 3
Classifier: License :: OSI Approved :: Academic Free License (AFL)
Classifier: Operating System :: OS Independent
Requires-Python: >=3.6
Requires-Dist: biopython
